homeslice/__init__.py
homeslice/__version__.py
homeslice/cli.py
homeslice/dircontext.py
homeslice/environments.py
homeslice/git.py
homeslice/pep508checker.py
homeslice/symlink.py
homeslice/utils.py
homeslice/commands/__init__.py
homeslice/commands/cmd_clone.py
homeslice/commands/cmd_config.py
homeslice/commands/cmd_link.py
homeslice/commands/cmd_list.py
homeslice/commands/cmd_pull.py
homeslice/commands/cmd_remove.py
homeslice/commands/cmd_unlink.py
homeslice-0.2.0.dist-info/DESCRIPTION.rst
homeslice-0.2.0.dist-info/LICENSE.txt
homeslice-0.2.0.dist-info/METADATA
homeslice-0.2.0.dist-info/RECORD
homeslice-0.2.0.dist-info/WHEEL
homeslice-0.2.0.dist-info/entry_points.txt
homeslice-0.2.0.dist-info/metadata.json
homeslice-0.2.0.dist-info/top_level.txt
