Metadata-Version: 2.0
Name: homeslice
Version: 0.2.0
Summary: dotfiles and :pizza: management
Home-page: https://github.com/jefftriplett/homeslice
Author: Jeff Triplett
Author-email: jeff.triplett@gmail.com
License: MIT
Platform: UNKNOWN
Classifier: Development Status :: 4 - Beta
Classifier: Intended Audience :: End Users/Desktop
Classifier: Intended Audience :: System Administrators
Classifier: Topic :: System :: Installation/Setup
Classifier: Topic :: System :: Systems Administration
Classifier: License :: OSI Approved :: MIT License
Classifier: Programming Language :: Python :: 2
Classifier: Programming Language :: Python :: 2.7
Classifier: Programming Language :: Python :: 3
Classifier: Programming Language :: Python :: 3.4
Classifier: Programming Language :: Python :: 3.5
Classifier: Programming Language :: Python :: 3.6
Requires-Dist: click
Requires-Dist: click-completion
Requires-Dist: click-log
Requires-Dist: crayons
